pulse_eight_matrix_client/__init__.py
pulse_eight_matrix_client/caching_pulse_eight_matrix_client.py
pulse_eight_matrix_client/exceptions.py
pulse_eight_matrix_client/models.py
pulse_eight_matrix_client/pulse_eight_matrix_client.py
pulse_eight_matrix_client-0.5.0.dist-info/WHEEL
pulse_eight_matrix_client-0.5.0.dist-info/METADATA
pulse_eight_matrix_client-0.5.0.dist-info/RECORD
