Metadata-Version: 2.3
Name: pulse-eight-matrix-client
Version: 0.5.0
Summary: An async Python client for controlling Pulse8 HDBaseT Matrix devices via their REST API.
Author: foxy82
Author-email: foxy82 <foxy82.github@gmail.com>
Requires-Dist: aiohttp>=3.9.0
Requires-Dist: pydantic>=2.12.0
Requires-Dist: pytest>=7.0.0 ; extra == 'dev'
Requires-Dist: pytest-asyncio>=0.21.0 ; extra == 'dev'
Requires-Dist: pytest-aiohttp>=1.1.0 ; extra == 'dev'
Requires-Dist: pytest-cov>=4.0.0 ; extra == 'dev'
Requires-Python: >=3.12
Project-URL: Homepage, https://github.com/designer-living/pulse-eight-matrix-client
Project-URL: Issues, https://github.com/designer-living/pulse-eight-matrix-client/issues
Project-URL: Repository, https://github.com/designer-living/pulse-eight-matrix-client
Provides-Extra: dev
